purviewcli/__init__.py
purviewcli/__main__.py
purviewcli/cli/__init__.py
purviewcli/cli/account.py
purviewcli/cli/cli.py
purviewcli/cli/collections.py
purviewcli/cli/domain.py
purviewcli/cli/entity.py
purviewcli/cli/glossary.py
purviewcli/cli/health.py
purviewcli/cli/insight.py
purviewcli/cli/lineage.py
purviewcli/cli/management.py
purviewcli/cli/policystore.py
purviewcli/cli/relationship.py
purviewcli/cli/scan.py
purviewcli/cli/search.py
purviewcli/cli/share.py
purviewcli/cli/types.py
purviewcli/cli/unified_catalog.py
purviewcli/cli/workflow.py
purviewcli/client/__init__.py
purviewcli/client/_account.py
purviewcli/client/_collections.py
purviewcli/client/_domain.py
purviewcli/client/_entity.py
purviewcli/client/_glossary.py
purviewcli/client/_health.py
purviewcli/client/_insight.py
purviewcli/client/_lineage.py
purviewcli/client/_management.py
purviewcli/client/_policystore.py
purviewcli/client/_relationship.py
purviewcli/client/_scan.py
purviewcli/client/_search.py
purviewcli/client/_share.py
purviewcli/client/_types.py
purviewcli/client/_unified_catalog.py
purviewcli/client/_workflow.py
purviewcli/client/api_client.py
purviewcli/client/business_rules.py
purviewcli/client/config.py
purviewcli/client/data_quality.py
purviewcli/client/endpoint.py
purviewcli/client/endpoints.py
purviewcli/client/exceptions.py
purviewcli/client/lineage_visualization.py
purviewcli/client/monitoring_dashboard.py
purviewcli/client/rate_limiter.py
purviewcli/client/retry_handler.py
purviewcli/client/scanning_operations.py
purviewcli/client/settings.py
purviewcli/client/sync_client.py
purviewcli/plugins/__init__.py
purviewcli/plugins/plugin_system.py
pvw_cli-1.5.0.dist-info/METADATA
pvw_cli-1.5.0.dist-info/WHEEL
pvw_cli-1.5.0.dist-info/entry_points.txt
pvw_cli-1.5.0.dist-info/top_level.txt
pvw_cli-1.5.0.dist-info/RECORD
