Metadata-Version: 2.4
Name: pvw-cli
Version: 1.5.0
Summary: Microsoft Purview CLI with comprehensive automation capabilities
Author-email: AYOUB KEBAILI <keayoub@msn.com>
Maintainer-email: AYOUB KEBAILI <keayoub@msn.com>
License-Expression: MIT
Project-URL: Homepage, https://github.com/Keayoub/pvw-cli
Project-URL: Documentation, https://github.com/Keayoub/pvw-cli/wiki
Project-URL: Repository, https://github.com/Keayoub/pvw-cli.git
Project-URL: Bug Tracker, https://github.com/Keayoub/pvw-cli/issues
Project-URL: Source, https://github.com/Keayoub/pvw-cli
Keywords: azure,purview,cli,data,catalog,governance,automation,pvw
Classifier: Development Status :: 4 - Beta
Classifier: Intended Audience :: Developers
Classifier: Intended Audience :: System Administrators
Classifier: Operating System :: OS Independent
Classifier: Programming Language :: Python :: 3
Classifier: Programming Language :: Python :: 3.8
Classifier: Programming Language :: Python :: 3.9
Classifier: Programming Language :: Python :: 3.10
Classifier: Programming Language :: Python :: 3.11
Classifier: Programming Language :: Python :: 3.12
Classifier: Topic :: Software Development :: Libraries :: Python Modules
Classifier: Topic :: System :: Systems Administration
Classifier: Topic :: Database
Classifier: Topic :: Internet :: WWW/HTTP
Requires-Python: >=3.8
Requires-Dist: azure-identity>=1.12.0
Requires-Dist: azure-core>=1.24.0
Requires-Dist: click>=8.0.0
Requires-Dist: rich>=12.0.0
Requires-Dist: requests>=2.28.0
Requires-Dist: pandas>=1.5.0
Requires-Dist: aiohttp>=3.8.0
Requires-Dist: pydantic<2.12,>=1.10.0
Requires-Dist: PyYAML>=6.0
Requires-Dist: cryptography<46.0.0,>=41.0.5
Provides-Extra: dev
Requires-Dist: pytest>=7.0.0; extra == "dev"
Requires-Dist: pytest-asyncio>=0.20.0; extra == "dev"
Requires-Dist: pytest-cov>=4.0.0; extra == "dev"
Requires-Dist: black>=22.0.0; extra == "dev"
Requires-Dist: isort>=5.10.0; extra == "dev"
Requires-Dist: flake8>=5.0.0; extra == "dev"
Requires-Dist: mypy>=0.991; extra == "dev"
Requires-Dist: pre-commit>=2.20.0; extra == "dev"
Provides-Extra: docs
Requires-Dist: sphinx>=5.0.0; extra == "docs"
Requires-Dist: sphinx-rtd-theme>=1.0.0; extra == "docs"
Requires-Dist: myst-parser>=0.18.0; extra == "docs"
Provides-Extra: test
Requires-Dist: pytest>=7.0.0; extra == "test"
Requires-Dist: pytest-asyncio>=0.20.0; extra == "test"
Requires-Dist: pytest-cov>=4.0.0; extra == "test"
Requires-Dist: requests-mock>=1.9.0; extra == "test"
